{
    "lp_contract": "CurveTokenV3",
    "pool_types": ["eth", "arate", "crate"],
    "wrapped_contract": "rETH",
    "swap_address": "",
    "lp_token_address": "",
    "gauge_addresses": [""],
    "lp_constructor": {
        "name": "LSDx Pool",
        "symbol": "ETHx"
    },
    "swap_constructor": {
        "_A": 30,
        "_fee": 4000000,
        "_admin_fee": 5000000000
    },
    "coins": [
        {
            "name": "ETH",
            "decimals": 18,
            "tethered": false,
            "underlying_address": "0xEeeeeEeeeEeEeeEeEeEeeEEEeeeeEeeeeeeeEEeE"
        },
        {
            "name": "stETH",
            "decimals": 18,
            "tethered": false,
            "underlying_address": "0xae7ab96520de3a18e5e111b5eaab095312d7fe84"

        },
        {
            "name": "frxETH",
            "decimals": 18,
            "tethered": false,
            "underlying_address": "0x5E8422345238F34275888049021821E8E08CAa1f"
        },
        {
            "name": "rETH",
            "decimals": 18,
            "wrapped_decimals": 18,
            "tethered": false,
            "wrapped_address": "0xae78736cd615f374d3085123a210448e74fc6393"
        }
    ],
    "testing": {
        "initial_amount": 10000
    }
}
